[
    {
        "figure": "https://p1-juejin.byteimg.com/tos-cn-i-k3u1fbpfcp/c2a5347e792c4909a065968c279ffcd3~tplv-k3u1fbpfcp-jj-mark:3024:0:0:0:q75.awebp#?w=1304&h=734&s=1384950&e=jpg&b=2d54f3",
        "startTimeStamp": 1701187200000,
        "title": "签约作者招募",
        "docLink": "https://juejin.cn/post/7306356212601667638",
        "category": "特别活动",
        "endTimeStamp": 1703952000000,
        "lastModifiedTime": 1701693955000
    },
    {
        "figure": "https://p1-juejin.byteimg.com/tos-cn-i-k3u1fbpfcp/d93eef3864c14974bdabd4cc1b69145c~tplv-k3u1fbpfcp-watermark.image",
        "startTimeStamp": 1701792000000,
        "title": "千里马悬赏",
        "docLink": "https://juejin.cn/pin/7309158181842059314",
        "category": "特别活动",
        "endTimeStamp": 1703952000000,
        "lastModifiedTime": 1701862386000
    },
    {
        "figure": "https://p3-juejin.byteimg.com/tos-cn-i-k3u1fbpfcp/3e559ea76d2843fcac397f1e4bcf7a49~tplv-k3u1fbpfcp-jj:480:400:0:0:q75.awebp#?w=520&h=240&s=48269&e=jpg&b=73f3ef",
        "startTimeStamp": 1701619200000,
        "title": "技术博客节",
        "docLink": "https://juejin.cn/post/7308782855940866074",
        "category": "特别活动",
        "endTimeStamp": 1702137600000,
        "lastModifiedTime": 1701851836000
    }
]